extract_patches/__init__.py
extract_patches/_nbdev.py
extract_patches/core.py
extract_patches/laf.py
extract_patches-0.1.31.dist-info/LICENSE
extract_patches-0.1.31.dist-info/METADATA
extract_patches-0.1.31.dist-info/WHEEL
extract_patches-0.1.31.dist-info/entry_points.txt
extract_patches-0.1.31.dist-info/top_level.txt
extract_patches-0.1.31.dist-info/RECORD
