Metadata-Version: 2.1
Name: extract-patches
Version: 0.1.31
Summary: Function for local patch extraction from OpenCV keypoints with proper bluring
Home-page: https://github.com/ducha-aiki/extract_patches
Author: Dmytro Mishkin, Vassileios Balntas
Author-email: ducha.aiki@gmail.com
License: Apache Software License 2.0
Keywords: patch,opencv,local features,local descriptors
Platform: UNKNOWN
Classifier: Development Status :: 3 - Alpha
Classifier: Intended Audience :: Developers
Classifier: License :: OSI Approved :: Apache Software License
Classifier: Natural Language :: English
Classifier: Programming Language :: Python :: 3.6
Classifier: Programming Language :: Python :: 3.7
Classifier: Programming Language :: Python :: 3.8
Requires-Python: >=3.6
Requires-Dist: opencv-python
Requires-Dist: numpy
Requires-Dist: matplotlib
